[
    {
        "action": "Context actions",
        "app": "",
        "appArgs": [
        ],
        "appCwd": "",
        "conditions": [
            {
                "attributes": [
                ],
                "itemType": "*"
            }
        ],
        "title": "Context menu customization"
    },
    {
        "action": "",
        "app": "IVEditor",
        "appArgs": [
            "-l"
        ],
        "appCwd": "iveditor",
        "conditions": [
            {
                "attributes": [
                    {
                        "title": "name",
                        "value": "*"
                    }
                ],
                "itemType": "*"
            }
        ],
        "title": "List scriptable actions"
    },
    {
        "action": "",
        "app": "taste-xml-to-aadl",
        "appArgs": [
            "$PRJ_FOLDER"
        ],
        "appCwd": "",
        "conditions": [
            {
                "attributes": [
                    {
                        "title": "language",
                        "value": "SDL"
                    }
                ],
                "itemType": "Function"
            }
        ],
        "title": "Edit"
    },
    {
        "action": "",
        "app": "make",
        "appArgs": [
            "-C",
            "$PRJ_FOLDER"
        ],
        "appCwd": "$PRJ_FOLDER",
        "conditions": [
            {
                "attributes": [
                ],
                "itemType": "*"
            }
        ],
        "title": "Build system"
    }
]
